geminiapi/__init__.py
geminiapi/__main__.py
geminiapi/main.py
easyvideo2txt-0.1.2.dist-info/METADATA
easyvideo2txt-0.1.2.dist-info/WHEEL
easyvideo2txt-0.1.2.dist-info/entry_points.txt
easyvideo2txt-0.1.2.dist-info/top_level.txt
easyvideo2txt-0.1.2.dist-info/RECORD
